Metadata-Version: 2.1
Name: behalearn
Version: 3.0.1
Summary: Library for processing and visualizing behavioral biometric data
Home-page: https://gitlab.com/behametrics/behalearn
Author: Behametrics
Author-email: tp2018tim4@gmail.com
License: UNKNOWN
Platform: UNKNOWN
Classifier: Programming Language :: Python :: 3
Classifier: License :: OSI Approved :: MIT License
Classifier: Operating System :: Microsoft :: Windows
Classifier: Operating System :: POSIX
Classifier: Operating System :: Unix
Classifier: Operating System :: MacOS
Requires-Dist: numpy
Requires-Dist: pandas
Requires-Dist: scikit-learn
Requires-Dist: seaborn
Requires-Dist: bokeh
